PyNotifyYou/__init__.py
PyNotifyYou/ntfy.py
pynotifyyou-0.1.0.dist-info/METADATA
pynotifyyou-0.1.0.dist-info/WHEEL
pynotifyyou-0.1.0.dist-info/RECORD
