Metadata-Version: 2.1
Name: PyNotifyYou
Version: 0.1.0
Summary: 'A simple library for sending notifications
Home-page: https://github.com/shizamuru-dev/PyNotifyYou
License: MIT
Keywords: notification,push,ntfy
Author: Shizamuru
Author-email: mmihajlov534@gmail.com
Requires-Python: >=3.9,<4.0
Classifier: License :: OSI Approved :: MIT License
Classifier: Operating System :: OS Independent
Classifier: Programming Language :: Python :: 3
Classifier: Programming Language :: Python :: 3.9
Classifier: Programming Language :: Python :: 3.10
Classifier: Programming Language :: Python :: 3.11
Classifier: Programming Language :: Python :: 3.12
Requires-Dist: requests (>=2.31.0,<3.0.0)
